pymultipleis/__init__.py
pymultipleis/multieis.py
pymultipleis-0.2.5.dist-info/LICENSE.md
pymultipleis-0.2.5.dist-info/WHEEL
pymultipleis-0.2.5.dist-info/METADATA
pymultipleis-0.2.5.dist-info/RECORD
