Metadata-Version: 2.1
Name: pymultipleis
Version: 0.2.5
Summary: A library for fitting a sequence of electrochemical impedance spectra (JAX version).
Home-page: https://github.com/richinex/pymultipleis
License: MIT
Keywords: electrochemical impedance spectroscopy, batch fitting, multiple, jax
Author: Richard Chukwu
Author-email: richinex@gmail.com
Maintainer: Richard Chukwu
Maintainer-email: richinex@gmail.com
Requires-Python: >=3.8,<3.11
Classifier: Intended Audience :: Science/Research
Classifier: License :: OSI Approved :: MIT License
Classifier: Operating System :: OS Independent
Classifier: Programming Language :: Python :: 3
Classifier: Programming Language :: Python :: 3.10
Classifier: Programming Language :: Python :: 3.8
Classifier: Programming Language :: Python :: 3.9
Provides-Extra: docs
Requires-Dist: jax (>=0.3.17,<0.4.0)
Requires-Dist: jaxopt (==0.5.5)
Requires-Dist: matplotlib (==3.6.0)
Requires-Dist: numpy (>=1.23.3,<2.0.0)
Requires-Dist: pandas (>=1.5.0,<2.0.0)
Requires-Dist: scipy (==1.9.1)
Project-URL: Documentation, https://pymultipleis.readthedocs.io/en/latest/index.html
Project-URL: Repository, https://github.com/richinex/pymultipleis
